Workbook

Sheet Executive Summary
A1: Super Micro Computer, Inc. (NASDAQ: SMCI) -- Data Pack
A2: $ in millions unless noted; fiscal years ended June 30. Source: SEC EDGAR XBRL (10-K filings).
A4: Overview: SMCI designs and manufactures high-performance server and storage systems, with growth driven by AI/GPU data-center demand. Revenue scaled ~6x from FY2021 to FY2025 while gross margin compressed, and FY2024 saw a large inventory-driven cash outflow.
A6: Financial snapshot
B7: FY2021 | C7: FY2022 | D7: FY2023 | E7: FY2024 | F7: FY2025
A8: Revenue | B8: ='Historical Financials'!B5 -> 3557.4 | C8: ='Historical Financials'!C5 -> 5196.1 | D8: ='Historical Financials'!D5 -> 7123.5 | E8: ='Historical Financials'!E5 -> 14989.3 | F8: ='Historical Financials'!F5 -> 21972
A9: Revenue growth % | B9: ='Historical Financials'!B18 -> 0 | C9: ='Historical Financials'!C18 -> 0.46064542 | D9: ='Historical Financials'!D18 -> 0.37093205 | E9: ='Historical Financials'!E18 -> 1.1042044 | F9: ='Historical Financials'!F18 -> 0.46584564
A10: Gross margin % | B10: ='Historical Financials'!B8 -> 0.15025018 | C10: ='Historical Financials'!C8 -> 0.15396163 | D10: ='Historical Financials'!D8 -> 0.18010809 | E10: ='Historical Financials'!E8 -> 0.13752477 | F10: ='Historical Financials'!F8 -> 0.11059075
A11: Operating income | B11: ='Historical Financials'!B12 -> 123.9 | C11: ='Historical Financials'!C12 -> 335.2 | D11: ='Historical Financials'!D12 -> 761.1 | E11: ='Historical Financials'!E12 -> 1210.8 | F11: ='Historical Financials'!F12 -> 1253
A12: Net income | B12: ='Historical Financials'!B15 -> 111.9 | C12: ='Historical Financials'!C15 -> 285.2 | D12: ='Historical Financials'!D15 -> 640 | E12: ='Historical Financials'!E15 -> 1152.7 | F12: ='Historical Financials'!F15 -> 1048.9
A13: Operating cash flow | B13: ='Cash Flow'!B5 -> 123 | C13: ='Cash Flow'!C5 -> -440.8 | D13: ='Cash Flow'!D5 -> 663.6 | E13: ='Cash Flow'!E5 -> -2486 | F13: ='Cash Flow'!F5 -> 1659.5
A14: Cash and equivalents | B14: ='Balance Sheet'!B5 -> 232.3 | C14: ='Balance Sheet'!C5 -> 267.4 | D14: ='Balance Sheet'!D5 -> 440.5 | E14: ='Balance Sheet'!E5 -> 1669.8 | F14: ='Balance Sheet'!F5 -> 5169.9
A16: Highlights: 46.6% FY2025 revenue growth on Blackwell-generation demand; OCF swung from $(2,486)M (FY2024) to $1,660M (FY2025); $5.2B cash provides balance-sheet flexibility.
A17: Considerations: gross margin down ~270bps YoY (11.1% FY2025); net income declined 9% despite revenue growth; FY2024 10-K was filed late (Feb 2025) following auditor transition.

Sheet Historical Financials
A1: Super Micro Computer, Inc. -- Income Statement
A2: $ in millions; fiscal years ended June 30
B4: FY2021 | C4: FY2022 | D4: FY2023 | E4: FY2024 | F4: FY2025
A5: Revenue | B5: 3557.4 | C5: 5196.1 | D5: 7123.5 | E5: 14989.3 | F5: 21972 | G5: SEC EDGAR, FY2025 10-K (accn 0001375365-25-000027, filed 2025-08-28); FY2021-23 as restated in later filings
A6: Cost of sales | B6: =B5-B7 -> 3022.9 | C6: =C5-C7 -> 4396.1 | D6: =D5-D7 -> 5840.5 | E6: =E5-E7 -> 12927.9 | F6: =F5-F7 -> 19542.1 | G6: Derived: Revenue less Gross profit
A7: Gross profit | B7: 534.5 | C7: 800 | D7: 1283 | E7: 2061.4 | F7: 2429.9 | G7: SEC EDGAR, FY2025 10-K (accn 0001375365-25-000027, filed 2025-08-28)
A8: Gross margin % | B8: =B7/B5 -> 0.15025018 | C8: =C7/C5 -> 0.15396163 | D8: =D7/D5 -> 0.18010809 | E8: =E7/E5 -> 0.13752477 | F8: =F7/F5 -> 0.11059075
A10: Research & development | B10: 224.4 | C10: 272.3 | D10: 307.3 | E10: 463.5 | F10: 636.5 | G10: SEC EDGAR, FY2025 10-K (accn 0001375365-25-000027, filed 2025-08-28)
A11: SG&A and other opex | B11: =B7-B10-B12 -> 186.2 | C11: =C7-C10-C12 -> 192.5 | D11: =D7-D10-D12 -> 214.6 | E11: =E7-E10-E12 -> 387.1 | F11: =F7-F10-F12 -> 540.4 | G11: Derived: Gross profit less R&D less Operating income
A12: Operating income | B12: 123.9 | C12: 335.2 | D12: 761.1 | E12: 1210.8 | F12: 1253 | G12: SEC EDGAR, FY2025 10-K (accn 0001375365-25-000027, filed 2025-08-28)
A13: Operating margin % | B13: =B12/B5 -> 0.034828808 | C13: =C12/C5 -> 0.064509921 | D13: =D12/D5 -> 0.10684355 | E13: =E12/E5 -> 0.080777621 | F13: =F12/F5 -> 0.057027125
A15: Net income | B15: 111.9 | C15: 285.2 | D15: 640 | E15: 1152.7 | F15: 1048.9 | G15: SEC EDGAR, FY2025 10-K (accn 0001375365-25-000027, filed 2025-08-28)
A16: Net margin % | B16: =B15/B5 -> 0.031455557 | C16: =C15/C5 -> 0.054887319 | D16: =D15/D5 -> 0.089843476 | E16: =E15/E5 -> 0.076901523 | F16: =F15/F5 -> 0.04773803
A18: Revenue growth % | C18: =C5/B5-1 -> 0.46064542 | D18: =D5/C5-1 -> 0.37093205 | E18: =E5/D5-1 -> 1.1042044 | F18: =F5/E5-1 -> 0.46584564 | G18: FY2021 growth n/a (FY2020 not presented)

Sheet Balance Sheet
A1: Super Micro Computer, Inc. -- Balance Sheet (selected items)
A2: $ in millions; as of June 30. Selected working-capital items only -- full statement pending broader data ingestion
B4: FY2021 | C4: FY2022 | D4: FY2023 | E4: FY2024 | F4: FY2025
A5: Cash and equivalents | B5: 232.3 | C5: 267.4 | D5: 440.5 | E5: 1669.8 | F5: 5169.9 | G5: SEC EDGAR, FY2025 10-K (accn 0001375365-25-000027, filed 2025-08-28)
A6: Accounts receivable, net | B6: 463.8 | C6: 834.5 | D6: 1148.3 | E6: 2737.3 | F6: 2203.9 | G6: SEC EDGAR, FY2025 10-K (accn 0001375365-25-000027, filed 2025-08-28)
A7: Inventory, net | B7: 1041 | C7: 1545.6 | D7: 1445.6 | E7: 4333 | F7: 4680.4 | G7: SEC EDGAR, FY2025 10-K (accn 0001375365-25-000027, filed 2025-08-28)
A8: Cash + AR + Inventory | B8: =SUM(B5:B7) -> 1737.1 | C8: =SUM(C5:C7) -> 2647.5 | D8: =SUM(D5:D7) -> 3034.4 | E8: =SUM(E5:E7) -> 8740.1 | F8: =SUM(F5:F7) -> 12054.2

Sheet Cash Flow
A1: Super Micro Computer, Inc. -- Cash Flow (selected items)
A2: $ in millions; fiscal years ended June 30
B4: FY2021 | C4: FY2022 | D4: FY2023 | E4: FY2024 | F4: FY2025
A5: Net cash from operating activities | B5: 123 | C5: -440.8 | D5: 663.6 | E5: -2486 | F5: 1659.5 | G5: SEC EDGAR, FY2025 10-K (accn 0001375365-25-000027, filed 2025-08-28); FY2024 per delayed 10-K (SEC EDGAR, FY2024 10-K (accn 0001375365-25-000004, filed 2025-02-25))
A6: Memo: Net income (link) | B6: ='Historical Financials'!B15 -> 111.9 | C6: ='Historical Financials'!C15 -> 285.2 | D6: ='Historical Financials'!D15 -> 640 | E6: ='Historical Financials'!E15 -> 1152.7 | F6: ='Historical Financials'!F15 -> 1048.9
A7: OCF / Net income conversion | B7: =B5/B6 -> 1.0991957 | C7: =C5/C6 -> -1.545582 | D7: =D5/D6 -> 1.036875 | E7: =E5/E6 -> -2.1566756 | F7: =F5/F6 -> 1.5821337

Sheet Operating Metrics
A1: Super Micro Computer, Inc. -- Operating Metrics
A2: Ratios computed from statement tabs; fiscal years ended June 30
B4: FY2021 | C4: FY2022 | D4: FY2023 | E4: FY2024 | F4: FY2025
A5: Days sales outstanding (DSO) | B5: ='Balance Sheet'!B6/'Historical Financials'!B5*365 -> 47.587283 | C5: ='Balance Sheet'!C6/'Historical Financials'!C5*365 -> 58.619445 | D5: ='Balance Sheet'!D6/'Historical Financials'!D5*365 -> 58.83758 | E5: ='Balance Sheet'!E6/'Historical Financials'!E5*365 -> 66.655181 | F5: ='Balance Sheet'!F6/'Historical Financials'!F5*365 -> 36.611301 | G5: Period-end AR / revenue x 365
A6: Days inventory outstanding (DIO) | B6: ='Balance Sheet'!B7/'Historical Financials'!B6*365 -> 125.69552 | C6: ='Balance Sheet'!C7/'Historical Financials'!C6*365 -> 128.32829 | D6: ='Balance Sheet'!D7/'Historical Financials'!D6*365 -> 90.342265 | E6: ='Balance Sheet'!E7/'Historical Financials'!E6*365 -> 122.3358 | F6: ='Balance Sheet'!F7/'Historical Financials'!F6*365 -> 87.418752 | G6: Period-end inventory / COGS x 365
A7: R&D % of revenue | B7: ='Historical Financials'!B10/'Historical Financials'!B5 -> 0.063079777 | C7: ='Historical Financials'!C10/'Historical Financials'!C5 -> 0.052404688 | D7: ='Historical Financials'!D10/'Historical Financials'!D5 -> 0.043138906 | E7: ='Historical Financials'!E10/'Historical Financials'!E5 -> 0.030922058 | F7: ='Historical Financials'!F10/'Historical Financials'!F5 -> 0.028968687
